{"endpoints":[{"id":"search_watch","name":"Watch search","path":"/search/watch"},{"id":"watch_info","name":"Watch info","path":"/watch/info"},{"id":"watch_price_1y","name":"Price history (1y)","path":"/watch/price_1y"}],"entries":[{"ts":"2026-07-18T04:04:03Z","checks":[{"id":"brand_list","status":"warn","code":403,"latency_ms":607,"error":"Invalid API key"},{"id":"search_watch","status":"warn","code":403,"latency_ms":500,"error":"Invalid API key"},{"id":"watch_info","status":"warn","code":403,"latency_ms":379,"error":"Invalid API key"}]},{"ts":"2026-07-18T04:42:07Z","checks":[{"id":"brand_list","status":"warn","code":403,"latency_ms":1103,"error":"Invalid API key"},{"id":"search_watch","status":"warn","code":403,"latency_ms":241,"error":"Invalid API key"},{"id":"watch_info","status":"warn","code":403,"latency_ms":144,"error":"Invalid API key"}]},{"ts":"2026-07-18T04:46:37Z","checks":[{"id":"brand_list","status":"degraded","code":200,"latency_ms":6858,"error":null},{"id":"search_watch","status":"up","code":200,"latency_ms":737,"error":null},{"id":"watch_info","status":"up","code":200,"latency_ms":918,"error":null}]},{"ts":"2026-07-18T04:56:15Z","checks":[{"id":"search_watch","status":"up","code":200,"latency_ms":1792,"error":null},{"id":"watch_info","status":"up","code":200,"latency_ms":1490,"error":null},{"id":"watch_price_1y","status":"up","code":200,"latency_ms":2979,"error":null}]}]}
